markblocks/__init__.py
markblocks/ast/__init__.py
markblocks/ast/metanode.py
markblocks/ast/node.py
markblocks/core.py
markblocks/data.py
markblocks/lex/__init__.py
markblocks/lex/admonition_lexer.py
markblocks/lex/blockquote_lexer.py
markblocks/lex/fence_lexer.py
markblocks/lex/gentokens.py
markblocks/lex/heading_lexer.py
markblocks/lex/inline_lexer.py
markblocks/lex/lexer.py
markblocks/lex/list_lexer.py
markblocks/lex/multilexer.py
markblocks/lex/scanner.py
markblocks/lex/table_lexer.py
markblocks/lex/taglexer.py
markblocks/lex/token.py
markblocks/lex/tokens.py
markblocks/lex/tokens.txt
markblocks/parse/__init__.py
markblocks/parse/parser.py
markblocks/render/admonition_renderer_mixin.py
markblocks/render/default_renderer.py
markblocks/render/emoji_renderer_mixin.py
markblocks/render/fence_renderer_mixin.py
markblocks/render/link_renderer_mixin.py
markblocks/render/renderer.py
markblocks/render/renderer_base.py
markblocks/render/table_renderer_mixin.py
markblocks/scope.py
markblocks/sly/__init__.py
markblocks/sly/ast.py
markblocks/sly/docparse.py
markblocks/sly/lex.py
markblocks/sly/yacc.py
markblocks/visitor.py
markblocks-0.1.0.dist-info/METADATA
markblocks-0.1.0.dist-info/WHEEL
markblocks-0.1.0.dist-info/RECORD
